Metadata-Version: 1.0
Name: pymorph
Version: 0.94
Summary: Image Morphology Toolbox
Home-page: http://luispedro.org/software/pymorph/
Author: Luis Pedro Coelho
Author-email: lpc@cmu.edu
License: BSD
Platform: UNKNOWN
